paquete_regresion_hugo/__init__.py
paquete_regresion_hugo/proyecto7.py
paquete_regresion_hugo-0.0.2.dist-info/LICENSE
paquete_regresion_hugo-0.0.2.dist-info/METADATA
paquete_regresion_hugo-0.0.2.dist-info/WHEEL
paquete_regresion_hugo-0.0.2.dist-info/top_level.txt
paquete_regresion_hugo-0.0.2.dist-info/RECORD
