Metadata-Version: 2.1
Name: paquete-regresion-hugo
Version: 0.0.2
Summary: Paquete de regresion para el proyecto 7 de la clase de ML
Author-email: Hugo Fonseca <hugofonseca@usantotomas.edu.co>
Project-URL: Homepage, https://github.com/zack0712/paquete_regresion_hugo
Project-URL: Bug Tracker, https://github.com/zack0712/paquete_regresion_hugo/issues
Classifier: Programming Language :: Python :: 3
Classifier: License :: OSI Approved :: MIT License
Classifier: Operating System :: OS Independent
Requires-Python: >=3.7
License-File: LICENSE
